QtPyNetwork/__init__.py
QtPyNetwork/__main__.py
QtPyNetwork/common.py
QtPyNetwork/balancer/AbstractBalancer.py
QtPyNetwork/balancer/NoBalancer.py
QtPyNetwork/balancer/ThreadBalancer.py
QtPyNetwork/balancer/ThreadPoolBalancer.py
QtPyNetwork/balancer/__init__.py
QtPyNetwork/client/AbstractClient.py
QtPyNetwork/client/TCPClient.py
QtPyNetwork/client/ThreadedTCPClient.py
QtPyNetwork/client/UDPClient.py
QtPyNetwork/client/__init__.py
QtPyNetwork/exception/__init__.py
QtPyNetwork/model/Client.py
QtPyNetwork/model/__init__.py
QtPyNetwork/server/AbstractServer.py
QtPyNetwork/server/TCPServer.py
QtPyNetwork/server/UDPServer.py
QtPyNetwork/server/__init__.py
examples/__init__.py
examples/tcp_balanced_server.py
examples/tcp_client.py
examples/tcp_interactive_client.py
examples/tcp_interactive_threaded_client.py
examples/tcp_no_balancer_server.py
examples/tcp_thread_pool_server_inheritance.py
examples/tcp_threaded_server.py
QtPyNetwork-0.7.0.dist-info/LICENSE
QtPyNetwork-0.7.0.dist-info/METADATA
QtPyNetwork-0.7.0.dist-info/WHEEL
QtPyNetwork-0.7.0.dist-info/top_level.txt
QtPyNetwork-0.7.0.dist-info/RECORD
