Metadata-Version: 2.1
Name: QtPyNetwork
Version: 0.7.0
Summary: Abstraction layer for Python Qt networks.
Home-page: UNKNOWN
Author: Wojciech Wentland
Author-email: wojciech.wentland@int.pl
License: MIT
Project-URL: Issues, https://github.com/desty2k/QtPyNetwork/issues
Project-URL: Docs, https://desty2k.github.io/QtPyNetwork/
Keywords: server,client,pyqt5,pyside2,qtpy,tcp
Platform: UNKNOWN
Classifier: Development Status :: 5 - Production/Stable
Classifier: License :: OSI Approved :: MIT License
Classifier: Programming Language :: Python :: 3.6
Classifier: Programming Language :: Python :: 3.7
Classifier: Programming Language :: Python :: 3.8
Classifier: Programming Language :: Python :: 3.9
Classifier: Programming Language :: Python :: Implementation :: CPython
Classifier: Intended Audience :: Developers
Classifier: Intended Audience :: Information Technology
Classifier: Topic :: Software Development :: Libraries :: Python Modules
Requires-Python: >=3.6
License-File: LICENSE
